pywe_pay_notify/__init__.py
pywe_pay_notify/compat.py
pywe_pay_notify/paynotify.py
pywe_pay_notify-1.0.5.dist-info/METADATA
pywe_pay_notify-1.0.5.dist-info/WHEEL
pywe_pay_notify-1.0.5.dist-info/top_level.txt
pywe_pay_notify-1.0.5.dist-info/RECORD
